README.md
setup.cfg
setup.py
pvdn/__init__.py
pvdn/core.py
pvdn/keypoints.py
pvdn/meta.py
pvdn.egg-info/PKG-INFO
pvdn.egg-info/SOURCES.txt
pvdn.egg-info/dependency_links.txt
pvdn.egg-info/requires.txt
pvdn.egg-info/top_level.txt
pvdn/filters/__init__.py
pvdn/filters/aperture.py
pvdn/filters/filter.py