Metadata-Version: 1.0
Name: pvdn
Version: 1.0
Summary: Tools for working with the PVDN dataset.
Home-page: https://github.com/larsOhne/pvdn
Author: Lars Ohnemus, Lukas Ewecker, Ebubekir Asan, Stefan Roos, Simon Isele, Jakob Ketterer, Leopold Müller, and Sascha Saralajew
Author-email: UNKNOWN
License: Creative Commons Legal Code 
Platform: UNKNOWN
